upt_cpan/__init__.py
upt_cpan/upt_cpan.py
upt_cpan/tests/__init__.py
upt_cpan/tests/test_upt_cpan.py
upt_cpan-0.6.1.dist-info/LICENSE
upt_cpan-0.6.1.dist-info/METADATA
upt_cpan-0.6.1.dist-info/WHEEL
upt_cpan-0.6.1.dist-info/entry_points.txt
upt_cpan-0.6.1.dist-info/top_level.txt
upt_cpan-0.6.1.dist-info/RECORD
