Metadata-Version: 2.1
Name: upt-cpan
Version: 0.6.1
Summary: CPAN frontend for upt
Home-page: https://framagit.org/upt/upt-cpan
Author: Cyril Roelandt
Author-email: tipecaml@gmail.com
License: UNKNOWN
Platform: UNKNOWN
Classifier: Development Status :: 3 - Alpha
Classifier: License :: OSI Approved :: BSD License
Classifier: Programming Language :: Python :: 3
Classifier: Programming Language :: Python :: 3.6
Classifier: Programming Language :: Python :: 3.7
Classifier: Programming Language :: Python :: 3 :: Only
Requires-Dist: requests
Requires-Dist: upt (>=0.6)
Provides-Extra: test
Requires-Dist: requests-mock ; extra == 'test'
